{
  "analysis": {
    "basic_stats": {
      "average": 877.25,
      "median": 850.5,
      "min": 580.75,
      "max": 1150.25
    },
    "patterns": {
      "seasonal": {
        "winter": {
          "average": 1037.17,
          "range": "2023-01 to 2023-03"
        },
        "spring": {
          "average": 760.83,
          "range": "2023-04 to 2023-06"
        },
        "summer": {
          "average": 940.83,
          "range": "2023-07 to 2023-09"
        },
        "fall": {
          "average": 826.67,
          "range": "2023-10 to 2023-12"
        }
      },
      "trends": {
        "increasing": {
          "months": [
            "2023-01",
            "2023-02",
            "2023-07",
            "2023-08",
            "2023-12"
          ]
        },
        "decreasing": {
          "months": [
            "2023-03",
            "2023-04",
            "2023-05",
            "2023-06",
            "2023-09",
            "2023-10",
            "2023-11"
          ]
        }
      }
    },
    "anomalies": {
      "high": {
        "month": "2023-01",
        "value": 1150.25
      },
      "low": {
        "month": "2023-05",
        "value": 580.75
      }
    },
    "insights": [
      {
        "month": "2023-01",
        "insight": "Highest consumption recorded, likely due to extreme cold weather."
      },
      {
        "month": "2023-05",
        "insight": "Lowest consumption recorded, likely due to mild weather."
      },
      {
        "month": "2023-07 to 2023-09",
        "insight": "Consumption increases during the summer months, likely due to air conditioning usage."
      },
      {
        "month": "2023-10 to 2023-12",
        "insight": "Consumption decreases during the fall months, likely due to mild weather and reduced heating needs."
      }
    ]
  },
  "recommendations": {
    "immediate_actions": [
      "Conduct an energy audit to identify areas of inefficiency in the home.",
      "Adjust thermostat settings to optimize heating and cooling usage."
    ],
    "seasonal_recommendations": {
      "winter": [
        "Increase insulation to reduce heat loss.",
        "Use energy-efficient heating systems."
      ],
      "spring": [
        "Optimize HVAC usage based on mild weather conditions.",
        "Consider using renewable energy sources."
      ],
      "summer": [
        "Optimize air conditioning usage to reduce energy consumption.",
        "Increase shading devices to reduce solar heat gain."
      ],
      "fall": [
        "Reduce heating usage as weather becomes milder.",
        "Prepare for winter by maintaining heating systems."
      ]
    },
    "long_term_improvements": [
      "Install energy-efficient windows to reduce heat loss and gain.",
      "Upgrade to energy-efficient HVAC systems."
    ],
    "behavioral_changes": [
      "Regularly monitor and adjust energy usage based on seasonal changes.",
      "Implement energy-saving habits, such as turning off lights when not in use."
    ]
  },
  "timestamp": "2024-11-07T18:10:45.993549"
}